MANIFEST.in
README.md
setup.py
hijricalendar/__init__.py
hijricalendar/__init__.pyc
hijricalendar.egg-info/PKG-INFO
hijricalendar.egg-info/SOURCES.txt
hijricalendar.egg-info/dependency_links.txt
hijricalendar.egg-info/not-zip-safe
hijricalendar.egg-info/requires.txt
hijricalendar.egg-info/top_level.txt