Metadata-Version: 1.1
Name: hijricalendar
Version: 0.0.1
Summary: Hijri Calendar is a package for Bangla language users with various functionalities including Arabic date in bangla and english format
Home-page: https://github.com/hmtanbir/hijricalendar
Author: Hasan Mohammad Tanbir
Author-email: tanbir2025@gmail.com
License: MIT
Keywords: arabic calendar hijri calendar
Platform: UNKNOWN
Classifier: Operating System :: OS Independent
Classifier: Programming Language :: Python :: 2.7
Classifier: Programming Language :: Python :: 3.3
Classifier: Programming Language :: Python :: 3.4
Classifier: Programming Language :: Python :: 3.5
Classifier: Programming Language :: Python :: 3.6
Classifier: Intended Audience :: Developers
Classifier: License :: OSI Approved :: MIT License
Classifier: Development Status :: 5 - Production/Stable
Classifier: Topic :: Software Development :: Libraries :: Python Modules
